aura/__init__.py
aura/api_command.py
aura/api_repository.py
aura/aura.py
aura/config_repository.py
aura/decorators.py
aura/error_handler.py
aura/format.py
aura/logger.py
aura/token_repository.py
aura/version.py
aura/config/__init__.py
aura/config/get.py
aura/config/list.py
aura/config/set.py
aura/config/unset.py
aura/config/valid_options.py
aura/credentials/__init__.py
aura/credentials/add.py
aura/credentials/current.py
aura/credentials/delete.py
aura/credentials/list.py
aura/credentials/use.py
aura/data_apis/__init__.py
aura/data_apis/create.py
aura/data_apis/delete.py
aura/data_apis/get.py
aura/data_apis/list.py
aura/data_apis/update.py
aura/data_apis/util/__init__.py
aura/data_apis/util/type_definitions.py
aura/instances/__init__.py
aura/instances/create.py
aura/instances/delete.py
aura/instances/get.py
aura/instances/list.py
aura/instances/overwrite.py
aura/instances/pause.py
aura/instances/resume.py
aura/instances/update.py
aura/snapshots/__init__.py
aura/snapshots/create.py
aura/snapshots/get.py
aura/snapshots/list.py
aura/snapshots/restore.py
aura/tenants/__init__.py
aura/tenants/get.py
aura/tenants/get_metrics_integration.py
aura/tenants/list.py
aura/util/__init__.py
aura/util/get_instance_id.py
aura_cli-0.7.0.dist-info/LICENSE
aura_cli-0.7.0.dist-info/METADATA
aura_cli-0.7.0.dist-info/WHEEL
aura_cli-0.7.0.dist-info/entry_points.txt
aura_cli-0.7.0.dist-info/top_level.txt
aura_cli-0.7.0.dist-info/RECORD
