Metadata-Version: 2.2
Name: aura-cli
Version: 0.7.0
License-File: LICENSE
Requires-Dist: click<8.2.0,>=8.1.0
Requires-Dist: requests<3.0.0,>=2.0.0
Requires-Dist: PyYAML
Requires-Dist: graphql-core>=3.1.0
Dynamic: requires-dist
